{
  "data": [
    {
      "id": "1",
      "name": "item1",
      "text": "Hello World!",
      "imageUrl": "http://placehold.it/400x400"
    },
    {
      "id": "2",
      "name": "item2",
      "text": "Hello World!",
      "imageUrl": "http://placehold.it/400x400"
    },
    {
      "id": "3",
      "name": "item3",
      "text": "Hello World!",
      "imageUrl": "http://placehold.it/400x400"
    },
    {
      "id": "4",
      "name": "item4",
      "text": "Hello World!",
      "imageUrl": "http://placehold.it/400x400"
    },
    {
      "id": "5",
      "name": "item5",
      "text": "Hello World!",
      "imageUrl": "http://placehold.it/400x400"
    },
    {
      "id": "6",
      "name": "item6",
      "imageUrl": "http://placehold.it/400x400"
    },
    {
      "id": "7",
      "name": "item7",
      "text": "Hello World!",
      "imageUrl": "http://placehold.it/400x400"
    },
    {
      "id": "8",
      "name": "item8",
      "text": "Hello World!",
      "imageUrl": "http://placehold.it/400x400"
    },
    {
      "id": "9",
      "name": "item9",
      "text": "Hello World!",
      "imageUrl": "http://placehold.it/400x400"
    },
    {
      "id": "10",
      "name": "item10",
      "text": "Hello World!",
      "imageUrl": "http://placehold.it/400x400"
    },
    {
      "id": "11",
      "name": "item11",
      "text": "Hello World!",
      "imageUrl": "http://placehold.it/400x400"
    },
    {
      "id": "12",
      "name": "item12",
      "text": "Hello World!",
      "imageUrl": "http://placehold.it/400x400"
    },
    {
      "id": "13",
      "name": "item13",
      "text": "Hello World!",
      "imageUrl": "http://placehold.it/400x400"
    },
    {
      "id": "14",
      "name": "item14",
      "text": "Hello World!",
      "imageUrl": "http://placehold.it/400x400"
    },
    {
      "id": "15",
      "name": "item15",
      "text": "Hello World!",
      "imageUrl": "http://placehold.it/400x400"
    }
  ]
}